fast_pandas/__init__.py
fast_pandas/__version__.py
fast_pandas/core.py
fast_pandas-1.0.0.dist-info/DESCRIPTION.rst
fast_pandas-1.0.0.dist-info/METADATA
fast_pandas-1.0.0.dist-info/RECORD
fast_pandas-1.0.0.dist-info/WHEEL
fast_pandas-1.0.0.dist-info/metadata.json
fast_pandas-1.0.0.dist-info/top_level.txt
